README.rst
setup.cfg
setup.py
check_email_status/__init__.py
check_email_status/resolvers.py
check_email_status.egg-info/PKG-INFO
check_email_status.egg-info/SOURCES.txt
check_email_status.egg-info/dependency_links.txt
check_email_status.egg-info/requires.txt
check_email_status.egg-info/top_level.txt