Metadata-Version: 1.1
Name: check-email-status
Version: 1.1.2
Summary: Check the existence of a mailbox via SMTP.
Home-page: https://github.com/lumpywizard/check_email_status
Author: Adrien Howard
Author-email: lumpywizard@gmail.com
License: UNKNOWN
Download-URL: https://github.com/lumpywizard/check_email_status/tarball/1.1.2
Keywords: smtp,validation,status,mailbox,email
Platform: UNKNOWN
